aws_alb/__init__.py
aws_alb/alb_traffic_enum.py
aws_alb/alb_type.py
aws_alb/application_loadbalancer.py
aws_alb/listener_actions.py
aws_alb/loadbalancer_listeners.py
aws_alb/loadbalancer_sg.py
aws_alb/loadbalancer_sg_modifier.py
aws_alb/factories/__init__.py
aws_alb/factories/listener_factory.py
aws_alb/factories/target_group_factory.py
aws_alb/params/__init__.py
aws_alb/params/listener_params.py
aws_alb/params/target_group_params.py
aws_alb-4.3.0.dist-info/LICENSE
aws_alb-4.3.0.dist-info/METADATA
aws_alb-4.3.0.dist-info/WHEEL
aws_alb-4.3.0.dist-info/top_level.txt
aws_alb-4.3.0.dist-info/RECORD
