Metadata-Version: 2.1
Name: aws-alb
Version: 4.3.0
Summary: AWS CDK package that creates a highly opinionated application load balancer.
Home-page: https://github.com/idenfy/AwsAlb.git
Author: Laimonas Sutkus
Author-email: laimonas.sutkus@gmail.com (laimonas@idenfy.com)
License: GNU GENERAL PUBLIC LICENSE Version 3
Keywords: AWS CDK ALB ELB LoadBalancer
Platform: UNKNOWN
Classifier: Programming Language :: Python :: 3
Classifier: Operating System :: OS Independent
Requires-Dist: aws-cdk.core (<2.0.0,>=1.60.0)
Requires-Dist: aws-cdk.aws-elasticloadbalancingv2 (<2.0.0,>=1.60.0)
Requires-Dist: aws-cdk.aws-certificatemanager (<2.0.0,>=1.60.0)
